amdsmi/__init__.py
amdsmi/amdsmi_exception.py
amdsmi/amdsmi_interface.py
amdsmi/amdsmi_wrapper.py
amdsmi/rocm_smi_tool.py
amdsmi-23.0.0.4.dist-info/LICENSE
amdsmi-23.0.0.4.dist-info/METADATA
amdsmi-23.0.0.4.dist-info/WHEEL
amdsmi-23.0.0.4.dist-info/top_level.txt
amdsmi-23.0.0.4.dist-info/RECORD
