Metadata-Version: 2.1
Name: amdsmi
Version: 23.0.0.4
Summary: SMI LIB - AMD GPU Monitoring Library
Author-email: AMD <amd-smi.support@amd.com>
License: Copyright (c) 2019-2022 Advanced Micro Devices, Inc.
Project-URL: Homepage, https://github.com/RadeonOpenCompute/amdsmi
Requires-Python: >=3.7
License-File: LICENSE
Requires-Dist: PyYAML >=5.0
Requires-Dist: clang >=14.0
